starlette_authlib/__init__.py
starlette_authlib/middleware.py
starlette_authlib-0.3.15.dist-info/METADATA
starlette_authlib-0.3.15.dist-info/WHEEL
starlette_authlib-0.3.15.dist-info/licenses/LICENSE.md
starlette_authlib-0.3.15.dist-info/RECORD
