Metadata-Version: 2.4
Name: starlette-authlib
Version: 0.3.15
Summary: A drop-in replacement for Starlette session middleware, using authlib's jwt
License-File: LICENSE.md
Author: Alessandro Ogier
Author-email: alessandro.ogier@gmail.com
Requires-Python: >=3.8,<4.0
Classifier: Programming Language :: Python :: 3
Classifier: Programming Language :: Python :: 3.8
Classifier: Programming Language :: Python :: 3.9
Classifier: Programming Language :: Python :: 3.10
Classifier: Programming Language :: Python :: 3.11
Classifier: Programming Language :: Python :: 3.12
Classifier: Programming Language :: Python :: 3.13
Classifier: Programming Language :: Python :: 3.14
Requires-Dist: authlib (<1.7)
Requires-Dist: starlette (<0.53)
Project-URL: Repository, https://github.com/aogier/starlette-authlib
